setup.py
layout_patern_ex_forex_next3/__init__.py
layout_patern_ex_forex_next3/layout_patern_ex_forex_next3.py
layout_patern_ex_forex_next3.egg-info/PKG-INFO
layout_patern_ex_forex_next3.egg-info/SOURCES.txt
layout_patern_ex_forex_next3.egg-info/dependency_links.txt
layout_patern_ex_forex_next3.egg-info/not-zip-safe
layout_patern_ex_forex_next3.egg-info/top_level.txt