Metadata-Version: 1.0
Name: layout-patern-ex-forex-next3
Version: 1.20
Summary: layout_patern_ex_forex_next3
Home-page: UNKNOWN
Author: omid
Author-email: UNKNOWN
License: UNKNOWN
Platform: UNKNOWN
